[
    {
        "storyId": "story467281197",
        "imagesrc": "Null",
        "userId": "mohamed",
        "content": "ghhhh",
        "timestamp": "09-12-2024 14:30"
    },
    {
        "storyId": "story701478932",
        "imagesrc": "C:\\Users\\Victus\\Downloads\\downloaded images\\emoticon.png",
        "userId": "best",
        "content": "lab 10",
        "timestamp": "09-12-2024 22:09"
    },
    {
        "storyId": "story1339748426",
        "imagesrc": "Null",
        "userId": "rr",
        "content": "gweafewwfe",
        "timestamp": "09-12-2024 23:51"
    }
]